LICENSE
MANIFEST.in
README.rst
setup.py
google/__init__.py
google/cloud/__init__.py
google/cloud/vision/__init__.py
google/cloud/vision/v1/__init__.py
google/cloud/vision/v1/geometry_pb2.py
google/cloud/vision/v1/image_annotator_pb2.py
grpc_cloud_vision_v1.egg-info/PKG-INFO
grpc_cloud_vision_v1.egg-info/SOURCES.txt
grpc_cloud_vision_v1.egg-info/dependency_links.txt
grpc_cloud_vision_v1.egg-info/namespace_packages.txt
grpc_cloud_vision_v1.egg-info/requires.txt
grpc_cloud_vision_v1.egg-info/top_level.txt